{
  "creds": {
    "noiseKey": {
      "private": {
        "type": "Buffer",
        "data": "oNH+rzednDoT1XsH006OWa6lwcjdv+5RlWPHSTMzbn0="
      },
      "public": {
        "type": "Buffer",
        "data": "jmtLLJwodlCbmSuHfIN8wT5Xqz4NU2/tWI7osjwqtAM="
      }
    },
    "signedIdentityKey": {
      "private": {
        "type": "Buffer",
        "data": "iHvikAI42UgRk4YknpE4LWIZULjI4eZYi1uacWNw7GU="
      },
      "public": {
        "type": "Buffer",
        "data": "L8u8PFHQBlreiEMnw033efxoxwMWkeCxStxTyUxMAVQ="
      }
    },
    "signedPreKey": {
      "keyPair": {
        "private": {
          "type": "Buffer",
          "data": "cKoTxA6ibMJ0CueS88KqdFbA2Wgqa+lxH/7tQRGS9Us="
        },
        "public": {
          "type": "Buffer",
          "data": "OZzcfdyvL6bbKL7dB4N5pCjE/+frVARmUte4Bh6a+0A="
        }
      },
      "signature": {
        "type": "Buffer",
        "data": "tphn1hZNZVBmJj1B1OdaqCMUJUZqu5dM3Wm7FPQ6GY4oubKZa2vRX1NFkoyvHHhYEQIfxMxBCDO+5y8t56nqBw=="
      },
      "keyId": 1
    },
    "registrationId": 139,
    "advSecretKey": "sqV9JzTaKwC6fkYLqVyX6FX8Qi2onhxYcf6JEWr+xRQ=",
    "processedHistoryMessages": [
      {
        "key": {
          "remoteJid": "6283890585717@s.whatsapp.net",
          "fromMe": true,
          "id": "89B4FBAF3DF701A48471AAC5CFC059A8"
        },
        "timestamp": 1659519642
      },
      {
        "key": {
          "remoteJid": "6283890585717@s.whatsapp.net",
          "fromMe": true,
          "id": "A16B0A491E87372137A6B50CB8B72C12"
        },
        "timestamp": 1659519642
      },
      {
        "key": {
          "remoteJid": "6283890585717@s.whatsapp.net",
          "fromMe": true,
          "id": "024E6DDC75C0722EB5E9B0F551FA67EB"
        },
        "timestamp": 1659519644
      }
    ],
    "nextPreKeyId": 31,
    "firstUnuploadedPreKeyId": 31,
    "accountSettings": {
      "unarchiveChats": false
    },
    "account": {
      "details": "CO7+35kBEJSFqZcGGAM=",
      "accountSignature": "ytJj4FxS567TVEZqvYsrJxQk0Y0JPL0cKB5JYcPpek7MVtRvpJSt4Ec77gLSMKIh3g28mMKl5Lb+19FEPYedDQ==",
      "deviceSignature": "a2y+f+VTpRoTrgHtjbIaXj9spHoxhUH3pATXl6PB8WZuloblZO97CexEYUSLnbx1uUYS8eU3xNgAnH5sDgs8Cw=="
    },
    "me": {
      "id": "6283890585717:9@s.whatsapp.net",
      "name": "NAKANO MIKU"
    },
    "signalIdentities": [
      {
        "identifier": {
          "name": "6283890585717:9@s.whatsapp.net",
          "deviceId": 0
        },
        "identifierKey": {
          "type": "Buffer",
          "data": "BUVGN7c0lSVyKCaa6KGCrLfNlTpkz+E0goUwOrt+cJYG"
        }
      }
    ],
    "platform": "smba",
    "lastAccountSyncTimestamp": 1659519639,
    "myAppStateKeyId": "AAAAAK/V"
  },
  "keys": {
    "preKeys": {
      "1": {
        "private": {
          "type": "Buffer",
          "data": "QJluSgnrFLxFxwcDTRfnrC74J+/3cDgh7xU03D5fD0U="
        },
        "public": {
          "type": "Buffer",
          "data": "5y9n906rnqYmJTN6BseLQw0yZGmAvuyDEcJ//P9emks="
        }
      },
      "2": {
        "private": {
          "type": "Buffer",
          "data": "SDTPp0pZaUgjj2c1Q9usffsAlPQ/R1kUIHgTo+eK/lc="
        },
        "public": {
          "type": "Buffer",
          "data": "dco7WFiC4ycXtfsBGs/bHTdWvgPxOIaPwCfsobntPBo="
        }
      },
      "3": {
        "private": {
          "type": "Buffer",
          "data": "wJeOxarXQcB0Vb5yuMqEd0Yw2NEHly1yWyTfmG9mV24="
        },
        "public": {
          "type": "Buffer",
          "data": "Jmw3mpM1yYuot9haKW8nbtbEaBzLapobrgYRkdXO6HI="
        }
      },
      "4": {
        "private": {
          "type": "Buffer",
          "data": "yPkxUnOkdRQYsO2a3JzjxtL/OiOVmU9rHB7CRLh0vkY="
        },
        "public": {
          "type": "Buffer",
          "data": "abaISNXDcopyoEXLuSpmHlC16Y87UyrRxpSpZt3c+Ws="
        }
      },
      "5": {
        "private": {
          "type": "Buffer",
          "data": "OOIpYvmhtOq4eCyQXDdVnAzPmTCMBFlTh9Q7gGMBuFY="
        },
        "public": {
          "type": "Buffer",
          "data": "pgOMBFNktomX8pu+1/kISlDlTOCva9Ah9ZmsHFPznyE="
        }
      },
      "6": {
        "private": {
          "type": "Buffer",
          "data": "0GevEnCsL/3wYtxCe79aFysyCFEP7xgAf8wsyAqz4U0="
        },
        "public": {
          "type": "Buffer",
          "data": "3DNl4KNjbHFRVhB5kXdis7/GxSzhn8cYwY+k7r88xEs="
        }
      },
      "7": {
        "private": {
          "type": "Buffer",
          "data": "wCHawScKEON27sYlShF2r+BE2SXJ572Sn6aNlbhpmEw="
        },
        "public": {
          "type": "Buffer",
          "data": "ZSgY7harhuIbpZw/gIz/J/JrB82Q2ph3RVuC4vfdvAE="
        }
      },
      "8": {
        "private": {
          "type": "Buffer",
          "data": "YA0eme6Vtk8eu59ec5lkZ2Gtn9ZEMWo8JgqmlP1iXWM="
        },
        "public": {
          "type": "Buffer",
          "data": "yqXiIXVwiRZJLqpbzEiYe1NLpNJ3GOJH6ZujWSiibiM="
        }
      },
      "9": {
        "private": {
          "type": "Buffer",
          "data": "IByL+gCX6ihwaRVpW0FejXGB+/tAHgLM/+oLdxVajHE="
        },
        "public": {
          "type": "Buffer",
          "data": "H62sbdegBiiVAca5aExs0tct+qEPxGr3I3bkEcZ8tAg="
        }
      },
      "10": {
        "private": {
          "type": "Buffer",
          "data": "CKRLkJhyZgLBYiaUSIVd6cI3AUWmLeK6qrCQr2WUwUs="
        },
        "public": {
          "type": "Buffer",
          "data": "yVIcYRLGLRyNwjvcP1dpA6RGrH0ODPdBIcXGp/cczyU="
        }
      },
      "11": {
        "private": {
          "type": "Buffer",
          "data": "iFU+7N193btf1erGpUq2sBkgZd445q0dQFTnKTqhLnM="
        },
        "public": {
          "type": "Buffer",
          "data": "LHDTHyXkw+KQA0GKu39c0oxlmFUYThNQrOh08rs1ujg="
        }
      },
      "12": {
        "private": {
          "type": "Buffer",
          "data": "CHI3IZ4uqWpGkqZh9SbFILq+L4In8NOYq9Ykx8BVMnc="
        },
        "public": {
          "type": "Buffer",
          "data": "4wMC11ypUpDcLSVyCPk4xRAR6/oJqOkxqxmc/wZyOy8="
        }
      },
      "13": {
        "private": {
          "type": "Buffer",
          "data": "yOKZZug1seCwXfEXLv4oAeHbYTQit6cZjxIzvHe7PEs="
        },
        "public": {
          "type": "Buffer",
          "data": "psQRjq32aHTCDFKrkG+8ooJrnzWfvHfKeHsdhqFKuWc="
        }
      },
      "14": {
        "private": {
          "type": "Buffer",
          "data": "4PNsHlddYsy7wf7PxHtF2Rmv2wQBJRLtSuRWovQWPn8="
        },
        "public": {
          "type": "Buffer",
          "data": "UsYWvkwyj7iMcsht4uo1MIhUEzjwLmSdt5kwAJz7TAw="
        }
      },
      "15": null,
      "16": {
        "private": {
          "type": "Buffer",
          "data": "CCJ3mwm3HjCecj/cYHPSPUiwxlxAI5bt2FY2pqUmEH0="
        },
        "public": {
          "type": "Buffer",
          "data": "1S9iE1ksr4JYf8yryYzbRstytvf5ASEdslyH5RR/4yU="
        }
      },
      "17": {
        "private": {
          "type": "Buffer",
          "data": "UO9VWpXGTV6XnLcoNMwZQU7hZSidPbYKUoSfmbBrN1Y="
        },
        "public": {
          "type": "Buffer",
          "data": "EhRexE0cmczbKzhAkQR0eKMD7hdfOX0H5ai2lgff3VM="
        }
      },
      "18": {
        "private": {
          "type": "Buffer",
          "data": "QJ1p7pL3uuB//9Zy7yzQwouyAqoOddSPhA5LQVZ9/kI="
        },
        "public": {
          "type": "Buffer",
          "data": "d9URMVgZpF33KiSfA83h+mhL7A1yG3nlhjkxWpowVi0="
        }
      },
      "19": {
        "private": {
          "type": "Buffer",
          "data": "CANa/fIWYjiK9qDueNckbES41BNCan8Y5BC4Uhr0UnU="
        },
        "public": {
          "type": "Buffer",
          "data": "U7MB+OCK3yCWH3KXeKX88cvjm2al0nZmIem7twpkKXk="
        }
      },
      "20": {
        "private": {
          "type": "Buffer",
          "data": "IAqPmg8YtM7oSJnEKVsmrHEYOD2ta3BtKurPvUDyvGQ="
        },
        "public": {
          "type": "Buffer",
          "data": "CvQ/MRyFTGA3gc0dUou6spZYF+N2ts80904EkDnufWY="
        }
      },
      "21": {
        "private": {
          "type": "Buffer",
          "data": "kOfuea00DNfU2cOd2dEZdFjwLeH4joeYzlrvST5/w10="
        },
        "public": {
          "type": "Buffer",
          "data": "J3a+GXSHdAxivlcQ44gw9/WoHOQIgORB0rxY8kzX8V8="
        }
      },
      "22": {
        "private": {
          "type": "Buffer",
          "data": "cNV+Y2ChyTF+alnf3VvWU7Zo85Yk9E0lYpjnQ1RK/VY="
        },
        "public": {
          "type": "Buffer",
          "data": "OgbY0y52Q53tN8WV6Cf6rStbad5VbaWW1mQe+mi1RgA="
        }
      },
      "23": {
        "private": {
          "type": "Buffer",
          "data": "eBQlI0NhezrCaLzSONcq/pfSmJRER0ysO/QMCqsVU1k="
        },
        "public": {
          "type": "Buffer",
          "data": "1nI0yGB7MYERlbw7I6GYXYo9EsErAjg4Z56oeotxAAg="
        }
      },
      "24": {
        "private": {
          "type": "Buffer",
          "data": "YP0Uyvxa7RLNGMHNjGourSL2IAOwsHK/vv3Y2R8cfVk="
        },
        "public": {
          "type": "Buffer",
          "data": "+DpWZJOOi3xQYRzj8h+E95dipWsCnzV2vn9I/FHoMGw="
        }
      },
      "25": {
        "private": {
          "type": "Buffer",
          "data": "SGeHfcR4dNosVOnvxMk9Px4f+/nq0soXECTEaOkwR2I="
        },
        "public": {
          "type": "Buffer",
          "data": "zIE5TLB0zPdHYkubASB+XOJ2lArTBiexetnR5z3QBkg="
        }
      },
      "26": {
        "private": {
          "type": "Buffer",
          "data": "8FgSBbxl4hUTAvv1y0qjvTg3orlTLMl/bi+UZdFQ33I="
        },
        "public": {
          "type": "Buffer",
          "data": "5/c7ZOubh64nFtzIxJcFBPfVyRxzWx/47acvWa1EaEk="
        }
      },
      "27": {
        "private": {
          "type": "Buffer",
          "data": "EDYfFnVgNYcHpVzgLms2k5l8Nk8KSQUMaaUESpUF0kA="
        },
        "public": {
          "type": "Buffer",
          "data": "ZESNo/wLT+ypaBGFyTVgp3OSIcQP/lsk1R85yq3MLUQ="
        }
      },
      "28": {
        "private": {
          "type": "Buffer",
          "data": "ICgCbKPMmutN2005Q7RNCMHmFohu6v/mZS64Gr1tA34="
        },
        "public": {
          "type": "Buffer",
          "data": "9JZzKooEJ/bjyNt0BEbEBGBjGFXWp1H/mMXlr5pDYU4="
        }
      },
      "29": {
        "private": {
          "type": "Buffer",
          "data": "qOxW/7X6bHKvM91+DEpz3ZgRBa/YAwAdxjkdHRd+CUc="
        },
        "public": {
          "type": "Buffer",
          "data": "k8p76XotZ16gLRit0fHRWzMYl+ojMfIWt9wJTWTa/0w="
        }
      },
      "30": {
        "private": {
          "type": "Buffer",
          "data": "UKboCAJh154hwccaLhod6zmUjo4MZ8eXmjfIix+cYXg="
        },
        "public": {
          "type": "Buffer",
          "data": "ppSY+VuGPlJFl4yj+oGeW5koe610EiADmiTYg9obMTo="
        }
      }
    },
    "sessions": {
      "6283890585717.0": {
        "_sessions": {
          "Bf/8NVWjH+2R0GaekrLJ7+iyJadHV2NaREDlo9Pr/Q9/": {
            "registrationId": 1309629599,
            "currentRatchet": {
              "ephemeralKeyPair": {
                "pubKey": "Bb6IAzhUf8T02MExRjm7jb+tMjOM8X+0Q8F9vkozpjoV",
                "privKey": "QOUdDJNzf84uKiR0gwFLhXof62GyhMQIbntN/Ve6SmE="
              },
              "lastRemoteEphemeralKey": "BS8PArM8l88pT4dDOsLFWCRcQaQkjXwP577N5XZzbFl0",
              "previousCounter": 0,
              "rootKey": "DxHdVxjR0EM1ppMrPeSUbYhstcwcrKYG3laJMgUh/3c="
            },
            "indexInfo": {
              "baseKey": "Bf/8NVWjH+2R0GaekrLJ7+iyJadHV2NaREDlo9Pr/Q9/",
              "baseKeyType": 2,
              "closed": -1,
              "used": 1659519642314,
              "created": 1659519642314,
              "remoteIdentityKey": "BUVGN7c0lSVyKCaa6KGCrLfNlTpkz+E0goUwOrt+cJYG"
            },
            "_chains": {
              "BS8PArM8l88pT4dDOsLFWCRcQaQkjXwP577N5XZzbFl0": {
                "chainKey": {
                  "counter": 6,
                  "key": "bJbp5Z2JZ90U5+OHb9AuYf6WTPZ5Ss/brJO0e9bfqtI="
                },
                "chainType": 2,
                "messageKeys": {}
              },
              "Bb6IAzhUf8T02MExRjm7jb+tMjOM8X+0Q8F9vkozpjoV": {
                "chainKey": {
                  "counter": 3,
                  "key": "Y/5iqEkoDE6bMcaXpU4iYOyaoeRyqTj3Q1o/WR+HLAQ="
                },
                "chainType": 1,
                "messageKeys": {}
              }
            }
          }
        },
        "version": "v1"
      },
      "6283890585717:7.0": {
        "_sessions": {
          "BadaVMKVu0Ao6hf5x/zpS4po+avJGQ7CtBalfheDpaMb": {
            "registrationId": 119,
            "currentRatchet": {
              "ephemeralKeyPair": {
                "pubKey": "BVLx8ojLKiQ4jkyVEDKtUcDIhXFJPTBN7NwobT/9mNoW",
                "privKey": "0DlsPTWw5Nuazh9RopoPTUhXDe0SzM6Zr6qropgB/mE="
              },
              "lastRemoteEphemeralKey": "BcAa9LrW2gOcujCp9nWaNlIN7BYHmrvVnHdz4nlCb4pk",
              "previousCounter": 0,
              "rootKey": "r6731ufHdlW5vDZeJh7aMvJrojbKg5V3nVn8WIn4tjE="
            },
            "indexInfo": {
              "baseKey": "BadaVMKVu0Ao6hf5x/zpS4po+avJGQ7CtBalfheDpaMb",
              "baseKeyType": 1,
              "closed": -1,
              "used": 1659519650711,
              "created": 1659519650711,
              "remoteIdentityKey": "BYhwlYskF9Q3b8sWpIDpDRJlAVibv99cAurmLyzMrCAd"
            },
            "_chains": {
              "BVLx8ojLKiQ4jkyVEDKtUcDIhXFJPTBN7NwobT/9mNoW": {
                "chainKey": {
                  "counter": 1,
                  "key": "RHdgxtT1+GWW2yTayJwsXvFXddY6mJ6GS+Lepd0qSWo="
                },
                "chainType": 1,
                "messageKeys": {}
              }
            },
            "pendingPreKey": {
              "signedKeyId": 1,
              "baseKey": "BadaVMKVu0Ao6hf5x/zpS4po+avJGQ7CtBalfheDpaMb",
              "preKeyId": 1
            }
          }
        },
        "version": "v1"
      },
      "6283890585717:8.0": {
        "_sessions": {
          "Ba3hFaHoCTo1yA8R11Fi7ihDKGPldL+7t6cQ0ZNlzOk5": {
            "registrationId": 186,
            "currentRatchet": {
              "ephemeralKeyPair": {
                "pubKey": "BYl9R5MYrnNfCXBuqfR7dzpQWxNjGCFWXst7J7RPdIcZ",
                "privKey": "+ItgiMgFGl01iwI4R7HVLB8nFPTjABq7BHYvPmLyEmw="
              },
              "lastRemoteEphemeralKey": "BRqdQw3bvd7zxObMRJ6gUvgV+2kB0DICZXVVVemaFetx",
              "previousCounter": 0,
              "rootKey": "VYUDkGaQn0/rbqp4KevVZh/2+g5NXU27m/UKDRLubT4="
            },
            "indexInfo": {
              "baseKey": "Ba3hFaHoCTo1yA8R11Fi7ihDKGPldL+7t6cQ0ZNlzOk5",
              "baseKeyType": 1,
              "closed": -1,
              "used": 1659519650713,
              "created": 1659519650713,
              "remoteIdentityKey": "Bfve63iTOMSkJrmfkAgSHYVt1Fdq/yXW93r4c84mi0Ma"
            },
            "_chains": {
              "BYl9R5MYrnNfCXBuqfR7dzpQWxNjGCFWXst7J7RPdIcZ": {
                "chainKey": {
                  "counter": 1,
                  "key": "kB96n4d2rTKH5UX/XxFR7k+UFqv2aG1C0Y0vusKhokM="
                },
                "chainType": 1,
                "messageKeys": {}
              }
            },
            "pendingPreKey": {
              "signedKeyId": 1,
              "baseKey": "Ba3hFaHoCTo1yA8R11Fi7ihDKGPldL+7t6cQ0ZNlzOk5",
              "preKeyId": 25
            }
          }
        },
        "version": "v1"
      }
    },
    "appStateSyncKeys": {
      "AAAAAK/V": {
        "keyData": "Onh+YSlMxTjBvlxIxMIbDXg9vtnv8liMc/BrCZ253NI=",
        "fingerprint": {
          "rawId": 322436974,
          "currentIndex": 1,
          "deviceIndexes": [
            0,
            1
          ]
        },
        "timestamp": "1659499250364"
      }
    },
    "appStateVersions": {
      "critical_block": {
        "version": 1,
        "hash": {
          "type": "Buffer",
          "data": "hsB4ha6AvjjD0fScZ3DWfBYnr5c8iy9cQrjDFjGSBkbnOWROXw9nswrtNrcOmc1KweOLoZvAnqhgNDK/nzxRlT5POaMSOzAregi8hHAeBl+WLPL//u9wwab4W3MLzb3EERxRrQORWbbfBqjfMAsZchry2CNMMrY/5TSmfF1EHjs="
        },
        "indexValueMap": {
          "8q84JwAHJMm+BpfvCOYHiz3ym2SGm6vlDPn0VG+i4Tc=": {
            "valueMac": {
              "type": "Buffer",
              "data": "ckycEvroigwRV/ug0IE6shsE+z/bhSaKJCxUDCPaHT0="
            }
          },
          "uykJyjvkSZyrBad85A6+KPsEvge6+8lwVogDqd44VKo=": {
            "valueMac": {
              "type": "Buffer",
              "data": "GG2DI4msQnlz9XIKma8+ckmuHzbcdf4FzFYItfN9MIg="
            }
          }
        }
      },
      "critical_unblock_low": {
        "version": 2,
        "hash": {
          "type": "Buffer",
          "data": "BrB/xSDdLYMiJQ89pGSXiLsSHgnvRqruj6BWxcPDo1uEln8lxNEvw4TJTBoqfRvIAYukKiRLTyytvC4yJvdcLX4cHkrNs6q8egnGuhe9w8Mcf7Hwl2xUSwG4+H91dvV2y+lcuebrHE9QtbGHLYkQg8361e1Ow9YVWMYybTYMrpc="
        },
        "indexValueMap": {
          "nACNQEhVg4lsdzySkkWpv4p3+vzJiRUB43bRjv3cKbw=": {
            "valueMac": {
              "type": "Buffer",
              "data": "MmpPzgTpI5WnJXCO66gCjC+BMtRzv1BPqquAymMMy4U="
            }
          },
          "OGI2l0AsbuAEMdzvgZW95xosbASHdNetbS6uEGi+ywk=": {
            "valueMac": {
              "type": "Buffer",
              "data": "OdSMswYRN3pNcRUpRujNOCX7sFTOPW+mjI+6+S6nE/g="
            }
          },
          "pZMk5G+Cn4B0Efy35Rz2ebs6FyiM4ymI+nq3wbA69YE=": {
            "valueMac": {
              "type": "Buffer",
              "data": "aDUMpXl4zsHofTpyvIQDn1s/HIq1gLfE174zWUc6Zlo="
            }
          },
          "SZqnYBGjar4E4qF8G20x6SAj9Z+dCMhOtQvHOtu6ym8=": {
            "valueMac": {
              "type": "Buffer",
              "data": "F8SAWTwODq2uYoEQxQJTvysGC2D6CZAOPHym6d+3/WA="
            }
          },
          "TeW48ImQ5tWSrIxeH7Yf8KMUNUeDRtCrqbwHBFsZPnM=": {
            "valueMac": {
              "type": "Buffer",
              "data": "g0XA1aJfst2GDAgXRrSHlm7KXCaqwQdLhVloDj+VQRk="
            }
          },
          "dM6AUqedrZ4NhYQBFZfgw43XiyaHjtQkbFnRVeDi4UA=": {
            "valueMac": {
              "type": "Buffer",
              "data": "UFXAAPJH6ch+q09NoEHRITHG53M5msdeZhBxTE3SBqQ="
            }
          },
          "7a3Wupvt4Gbr1A181imf0cKwJHrf5ugh/D7LIr6FE98=": {
            "valueMac": {
              "type": "Buffer",
              "data": "lYkRZUkl/JIhyjKc0lHIKOVfiV2J+xqXOmNDM5R3K+Y="
            }
          },
          "GtBHLYpvukPJmk97UQ89UZBGI1ThkXV34LupD0luMyg=": {
            "valueMac": {
              "type": "Buffer",
              "data": "BNRQInxCue+mX/nsNKY6FtjbRR6N5XCg0NkWZPtGwGE="
            }
          },
          "7Z+BNBtyVOCUobfpDgFYJZh2johjRCNDX3lZ6crUIgU=": {
            "valueMac": {
              "type": "Buffer",
              "data": "N+OseXxjF6EQzbuhM3O8kl9lhhuxcgAstnEUKkK+n5g="
            }
          },
          "Nc6zCqX+oWZcie5TaOvFjCVco9TrZnum7yvF/rYsIUE=": {
            "valueMac": {
              "type": "Buffer",
              "data": "Rzq5i9bYnu12WIHZ8+SgVz+6bL9CngRls8L7kOYJAQ4="
            }
          },
          "ooNpqKBw8tUDeXv74H4Mr/II+y1aziEm6/4FOSDqeP4=": {
            "valueMac": {
              "type": "Buffer",
              "data": "YMsfQXibeDZT7nkKKZftoc/0Su+FOov7+7Eu5P8S2nE="
            }
          },
          "JgWIfU5JA8JLn3VwK3/sVsNmJpjGjRDcg0bALCD5hD4=": {
            "valueMac": {
              "type": "Buffer",
              "data": "lbbMNHovkun0/sxaYfxfFnxKpQNUw6uC8F2LY7k22Kc="
            }
          },
          "dNIVDmJ4XY/HCrytYSQ/YU0Gee8LpyoUV4zIrrHrE4U=": {
            "valueMac": {
              "type": "Buffer",
              "data": "s9VRU48rZdkfF9daijLMV//JDuKsfdscJJ6/eIg5tAc="
            }
          },
          "hRUX3IoJb+Am0cPJzMQ1SC23nLFVDmPySeOjvJsV0dY=": {
            "valueMac": {
              "type": "Buffer",
              "data": "FSIdLofi/J0gS5eG5GYQtqZseny/FXtcZ/d2auk45z0="
            }
          },
          "5blb3ydNKzFCRCccSoMSbWqFYZnmrqayRNlzaUJ4Jpk=": {
            "valueMac": {
              "type": "Buffer",
              "data": "0jrKCL+8yqQwp8EzsUI48+MiUy+EcQNG6SS6lXBSGpg="
            }
          },
          "Rrsx+TQcmB+jNEQZVhUKjuxybfocourwyQJ1++XnwZk=": {
            "valueMac": {
              "type": "Buffer",
              "data": "UZMuJLigH2s50SQcIlUrSxJMMPI0raWLXw3YQf81S/k="
            }
          },
          "6ZOhzdmcxfJGAWcOYPMFyMDeadkkwQxYNcOIpjUSxkc=": {
            "valueMac": {
              "type": "Buffer",
              "data": "Es5cn2Q9oIUh/EWLokDl3ZfP91cFx5khpy9V5o2bnUA="
            }
          },
          "ufMGkv8q/kYxdgvDh8txiBTDuD8zOq8Fw78/nA7zrYs=": {
            "valueMac": {
              "type": "Buffer",
              "data": "JDU5VnIz2wu9BM12l2grD5WJ2JC7yJJCv0ym0i9/vSg="
            }
          },
          "tPd2lbCj+HtA6748F54F+dxSIRMXBa4ka7JwmkVclJg=": {
            "valueMac": {
              "type": "Buffer",
              "data": "KFe0kg8VxbZlxpbXQfAfVsjuYOFMoNMBgA9J8Ar/I7g="
            }
          },
          "gIVhr8UaLr3ETCZdRDQqAsJhGtKy4Kd9sibxuu9x6Q0=": {
            "valueMac": {
              "type": "Buffer",
              "data": "1xZHOoZI+9gmShL9dtFXe4xJMNCe7cSA1uESd9kBwIs="
            }
          },
          "wmyvNYopmY36uVfr/2cny2byRoZpD5yU/vJfosof+sI=": {
            "valueMac": {
              "type": "Buffer",
              "data": "Za/r5s8vVUlxlHHW7bOjQL7Tbp++BgzANJPIW39fn9c="
            }
          },
          "2kg+gR+6P+7fMkli+YBx67v/HO0GT551mOuFiH6gl9Y=": {
            "valueMac": {
              "type": "Buffer",
              "data": "G4/237ViVrKfN+RXHiWsSwYdNO9b1hNVs774ZYBig9w="
            }
          },
          "R37zoNby30bZMmcBENiatmcpA6b4HBKVZrmdEIojAeM=": {
            "valueMac": {
              "type": "Buffer",
              "data": "lNTpf0xqYeWanNo53xnBKhnZBqgBu/j1rkiGhiIbChU="
            }
          },
          "zeGk584k9ov1tXbynmjU8SrPDnkjaSgeKprkS1IWhx0=": {
            "valueMac": {
              "type": "Buffer",
              "data": "t4rG4Nj1Vps4ap2jgc+Zqqd6qYwucdRdM/7LIpK8r0c="
            }
          },
          "8CtGUE5Mqjj41CxV4mCV0SFRX7PyugaJO/vpzyqTj1M=": {
            "valueMac": {
              "type": "Buffer",
              "data": "WJic72I9k8tOc9qZvoWBOHfFQMkaEuqTSPKf/2y/sXI="
            }
          },
          "DqGD7eKlaznrDsirtWDWAXHh6L8p16WofKRgw1cAihU=": {
            "valueMac": {
              "type": "Buffer",
              "data": "EiyrbcUeLoZ3OwK0FeEj7vrQNRurnDCDf6Xdz8rpclI="
            }
          },
          "cauImWd3MztYO+i6rnCjbR3M0+Guvw1xBZsLATjseqo=": {
            "valueMac": {
              "type": "Buffer",
              "data": "Aj8EC/sJUCa7BCw733ZIOOqLPCeA552WMHhWUUb3PN0="
            }
          },
          "3fpwQ/Go2fl1FuxBVBN22ThiF7Gug3lfJcfW19f7OGk=": {
            "valueMac": {
              "type": "Buffer",
              "data": "ksL5QbfpEaC9nn8eMrJZPDT1YUhCiJumsgX3rYFv7T4="
            }
          },
          "uXug6OgboWsaQ5d5nhIKx62tgx2Sctvab4EA1yCKHo8=": {
            "valueMac": {
              "type": "Buffer",
              "data": "gqw9SfXAEirvg88mgvp+Ga0/JH+L8oU/ZgM1OlM0HfY="
            }
          },
          "j0eH//PaJ9Hb5DMD1iJGdAiOgvMntg1ag0xoR/V3LtY=": {
            "valueMac": {
              "type": "Buffer",
              "data": "8c6DS3wZomhYvrqVmlX/kwfPCgPgIAHCNcYuSVmy/Z4="
            }
          },
          "sSzCohIUwYm7BFjc4fdFOE4ygukS+mHHLLSBebo5ziI=": {
            "valueMac": {
              "type": "Buffer",
              "data": "s8cqmebYd7kMctDM0t5FC7zJ60BCJUcGAYA0y0eP+DU="
            }
          },
          "uG5DRy1HNgStMikrjf1GVVI9xI8PqXpPI3tTvuAtao4=": {
            "valueMac": {
              "type": "Buffer",
              "data": "lxcNBI5lBp9XjLy8i21YW/D9TIQqNWAwRTPfunqhzM0="
            }
          },
          "21vsmHbHRqH77E6h5dBX1/lutKKH0Zp18NGTBDfs5cg=": {
            "valueMac": {
              "type": "Buffer",
              "data": "frhP8S0qMYVryfOTIhDXHXHy5d1HSkcOGZhT/SRTfVI="
            }
          },
          "EcI55wYwhTdkHjLwDGAXB92aepwgJUmDOALwcqUEYgQ=": {
            "valueMac": {
              "type": "Buffer",
              "data": "/8nnGoyF41Dsk/iEpjR7gL5v3TTY1oTMlDaGtelwRQA="
            }
          },
          "Vv6Z5AY3fpdznv7/79s/wvhqGywkywAzZHLIjShB81g=": {
            "valueMac": {
              "type": "Buffer",
              "data": "+fYNOUE8i1bRi++VyQxZVSnNZC+Svm0Z5MXjQu8dZVE="
            }
          },
          "zWjLFE617mkYDah04zbkxvUiHQ6RXHEh3MvVqKrAdAA=": {
            "valueMac": {
              "type": "Buffer",
              "data": "Z6jjrFUn69W6O1kvKXzldAzamt/IOGCtjkYXVjIz9HU="
            }
          },
          "sSmHni/BmAGY2BOOlYezUKoM3c3N4p6l8s880M8tJLc=": {
            "valueMac": {
              "type": "Buffer",
              "data": "LaYJ+jr9EAl4x9VxlkGWTuP6fDMRaZpFZQv9JkuWo+Q="
            }
          },
          "1O1hxGaRrp4L7YQfSiLwSFjjlLNSoExYtcJRwtE4cSw=": {
            "valueMac": {
              "type": "Buffer",
              "data": "DegGAvixIcpCuqTFxzN63eskR75CcQmmdNJGMKjdwxg="
            }
          },
          "2GTF9MIOwkzw6AQfgpkz6BoJbq/mZdRMfv6gkiAfE4Y=": {
            "valueMac": {
              "type": "Buffer",
              "data": "mzhk1vQrF05NNYSzvV+UWj5mNWiCQDVkPJh0yX/iDPo="
            }
          },
          "6gZjc832wmk0w5VVSnBWEXEEC0Wvd4gTvxyEUcQlL4o=": {
            "valueMac": {
              "type": "Buffer",
              "data": "Xi4srbI4+3FbvtPUQeM/57xOFsqzpSOhBRpWKtMTkVM="
            }
          },
          "KhxR+sAlKSn7kp3n9l7/SiURt7Fx/tsWlJ5qyELGMoY=": {
            "valueMac": {
              "type": "Buffer",
              "data": "JhV5hk75KGkDwxv8icy1vDNe2P8RDgzXWVul4s/lXSo="
            }
          },
          "LRaTIKGoOtGzhOWoKBg/KSeD5fuQSMR/xqdE70pa4AY=": {
            "valueMac": {
              "type": "Buffer",
              "data": "dQbw5d/iYlQWAxxfsy70DeH1YW2j/80oigQt4sh6i0Y="
            }
          },
          "NtqZUYlNckDl6rBV2SOkB5S9CWXGMvRoVugyzDTwcpI=": {
            "valueMac": {
              "type": "Buffer",
              "data": "bMggEin+sgbKSgC79Ug3l/Qsm4XKAWK/DMg3UpUnLd8="
            }
          },
          "L22A2ky0co5sZuS3idDi6iRl0aTX+6ohvfF/pJ+zXpI=": {
            "valueMac": {
              "type": "Buffer",
              "data": "bAxfltR5pv5t0DClT4z15IvLkQv9J9vwormX9KGnDN4="
            }
          },
          "sgxSs/hPBhObsJ8md9r15tKnVJogpTpJrh02eRBaNNs=": {
            "valueMac": {
              "type": "Buffer",
              "data": "3Xc1hcMbyE2IENZAzbRwA7vKbwAkk59k3bFxHtBk41I="
            }
          },
          "fvfSgpQnOQZ7mM0cnEdIalFY6GhfIJg42L9WrobrqBk=": {
            "valueMac": {
              "type": "Buffer",
              "data": "BmnJPqtEPT3EplPDpZd+v722rIsXlnTTfG3RiB6YupE="
            }
          },
          "gQvO557v/AOvhnlNCuGjWz0eiIBQS9cLjEWnFplpLXw=": {
            "valueMac": {
              "type": "Buffer",
              "data": "mJTeU24sJwhhSkvUtrQFYfmhkVdtCsQ0BdcpIivXk+M="
            }
          },
          "fzLzArGujvAl3sayzxw6WBnVKFyd8nUV/WeeNWcR1YE=": {
            "valueMac": {
              "type": "Buffer",
              "data": "+y5eA0Nqnvs9cKF2TJqRJPRCxjIFHZYv1nW4mOkuDkA="
            }
          },
          "t2Rjl7PuxJz0PIRJUZyiNuV/Q3aVhQHG+IYTkmzYe7E=": {
            "valueMac": {
              "type": "Buffer",
              "data": "SaBa9R3dI2lPPDVECFmqlwGEA+x3cWzbQtb7RhbrNf8="
            }
          },
          "Wl7miaTAuXywGEX32MwKrEm9TgPDmaMe7kN3eVZt5WU=": {
            "valueMac": {
              "type": "Buffer",
              "data": "cv8WvWge63/f1igrUMbbM0vZWBtypYfbXI5t/H/hFFA="
            }
          },
          "W9lOaf+AY94MZ5QlRFdAlpfZmvICF+6OWp+r/BUkDn4=": {
            "valueMac": {
              "type": "Buffer",
              "data": "ue5z2ghNEFI9S/ccCVmbUcAWOo/9nIl9gU3Bo/ZXvD0="
            }
          },
          "oEC4jlTewdsNRTz76ZByoova3IyzMIlMAZ19WW6rxko=": {
            "valueMac": {
              "type": "Buffer",
              "data": "/OQSdAJTJe706ZM0oncsxl/PqmMt2ji3BvGxwBkbSxU="
            }
          },
          "yXXbyDhgM9fwbAy+FKB83SjiorEdwISO79p7fKNETXE=": {
            "valueMac": {
              "type": "Buffer",
              "data": "BVcMgOo5OJnMpU/Heo4P06Wnx2eFeBdomjWoduzu/kw="
            }
          },
          "IoTG7opO7N/iiUH7CveGkeQg4/xptb+cOuKz+llHJr8=": {
            "valueMac": {
              "type": "Buffer",
              "data": "TromGkNsrsrw7nohQFpjsDwts4rQ2t+CjwhH+B7HesY="
            }
          },
          "4FwKsRxtWPcS5JKaTtNoLq/sIC7DDi5ma+yDpnVjLPg=": {
            "valueMac": {
              "type": "Buffer",
              "data": "6S8znDLlP0ok9m2iet75FSNItFfbLxpPmaEGEGZ3nQ8="
            }
          },
          "Q0/9ztwnbXOMEhVa4QziJ9ty8WLYGQymrndk+gtzT0s=": {
            "valueMac": {
              "type": "Buffer",
              "data": "VfI3vRhwkVY3nKR+knqkpXQ3BPfbN/RSCGazElYsbXo="
            }
          },
          "4p0RWXla7gnKF7L/BmKSAJCgDHNvTCd8Lw8PD7G1Gw0=": {
            "valueMac": {
              "type": "Buffer",
              "data": "qXgTBNuWS7UOOlY8DmLAb/9f3vgfVbCuobQzIUIEyLw="
            }
          },
          "rANuYsVGKu/sG9+jpSLb5xXg0xCR73ArP8Q0sL1ld8k=": {
            "valueMac": {
              "type": "Buffer",
              "data": "3dGN74tkn5SVpHK0dxkB6xeuYZTIfi8fk1ATJb6FivY="
            }
          },
          "9DOK0RnZgG7iowpBVv+qOtcXaHsF3fDlQ9JXe3o5p6o=": {
            "valueMac": {
              "type": "Buffer",
              "data": "9RnYx+9hPTjWkVNCunrPFTllSoPayC7lZ9zdIboTuvs="
            }
          },
          "Dnf9EfVNXLDm0j47BaaYsjh/26sw9s1x1S6Rrt4qnTk=": {
            "valueMac": {
              "type": "Buffer",
              "data": "Xs3oUb9QbODy29n/+ECkgTs3yrXJ1wmgC1UxLJyPhIc="
            }
          },
          "Y1FDchAWfp/oa2CruHSHVEj3iXIr+mbsEEEPub++a28=": {
            "valueMac": {
              "type": "Buffer",
              "data": "Utn59faW/oJpRqJp9plOxfrT9czPu+uIVpYPoTlblaw="
            }
          },
          "GBq4Ffz8AFHxBU4RjMphOpaXgC4XbejUlEcBTpVjrKU=": {
            "valueMac": {
              "type": "Buffer",
              "data": "gaH1fWFndodxuGZsEAlLpFhqxdxrBY2cg/7mZU5gUJ4="
            }
          },
          "WC/+sbTvMqUwTz1MvYW4SJIVffBD6tuLitIknYfBD3o=": {
            "valueMac": {
              "type": "Buffer",
              "data": "OokQ+wYnOZ2hzsn28p+Dpi8sxUzgRYx3HTf0i0RzmXc="
            }
          },
          "hCxc31Oa9IkX5hHdIXdmSQsiFl3Un5Cp8ocONYEIsVE=": {
            "valueMac": {
              "type": "Buffer",
              "data": "f2yNefozIRvHUUPvBCc1OJLpQkFBvS96+TEtxueSqnc="
            }
          },
          "GFl5mXdfoVvvUtjlRcA2jL3/LMBhFPvJKdSfNiC2++M=": {
            "valueMac": {
              "type": "Buffer",
              "data": "gJAPI5NTg7Y4G9totJfA3xe1ZLnZjz2JLG9Cthvnm/0="
            }
          },
          "c4VZ7Lwv14jVrMlWvXk5JNeeqkaIsOvtMvzvQC1UoxE=": {
            "valueMac": {
              "type": "Buffer",
              "data": "sFtFwiGNH5420EXC6ZlReJC+ibBLxr8BP8sIEmnEBno="
            }
          },
          "Wet83VcPjlO7lQ32mmgl2kMDP516bAJhihXZovDStcQ=": {
            "valueMac": {
              "type": "Buffer",
              "data": "tEwEN1B/BuZznU1OHXKX+CxIrq6oiMeO9GtRWzQ2vT8="
            }
          },
          "fY5bSowyYl+QsmfL2Fx94odRmTt3wdmtOmcqI6Draiw=": {
            "valueMac": {
              "type": "Buffer",
              "data": "Usibqmn9pAMQTrt5Fx1xIBRJx33suHIR5jysojL+MJU="
            }
          },
          "pm0xwhWtEJ3QrKh+kq06r6mIv9CzuXY8P6NhLPVao/Q=": {
            "valueMac": {
              "type": "Buffer",
              "data": "10gNbbtl1Dz4tsCaaSYwY7dxO3Cmhg+7vE87Awa5z1k="
            }
          },
          "WK6SfCLkP3A4FjkiyFdlFvZ0TXKxYjVQWR+dGUkAGSs=": {
            "valueMac": {
              "type": "Buffer",
              "data": "SUwW+PQi63ltoqyNIEzVuIeDl7TcsUb4YYM5rDYkICU="
            }
          },
          "toAdkE6owcp7nqsYAiljfVXTjsdF4hskNf9a39ShR2g=": {
            "valueMac": {
              "type": "Buffer",
              "data": "sA8eihgJcHJbsQhD4m2DVKI9GmxY7eajIUGFMsP7wTI="
            }
          }
        }
      },
      "regular": {
        "version": 2,
        "hash": {
          "type": "Buffer",
          "data": "hH7WGfyt4YX/3CqTAKrmv1H916TL0Pa2WBGgtR1xmk6IE2DO6XiM+sfSXlOotcEglZIefJizAXqWJfHkfI4VMm+5HgBbyMunMTenltTCei0bDPGNquiANzKBwdk/gCnOnbpfP62bklLlUhZTFVUqBRHjKMv/AUpsvqId/fTlERw="
        },
        "indexValueMap": {
          "Y8ggagG16nVBwPc8Elf/SuSpTKVwpHV1k2w2tvrEGqY=": {
            "valueMac": {
              "type": "Buffer",
              "data": "XzvKanogcGKb3XU5nd8jaPr9xicdy3Xrhr7kHaEddxA="
            }
          },
          "QIjQBKRz46P238Knxk/3I/HrzxvOnNXq4gk8PibgCpU=": {
            "valueMac": {
              "type": "Buffer",
              "data": "Td43KByodxgSXUoxPi9yIcmgwNTXRg+ziHtK5wJSmdA="
            }
          },
          "TfwCCdSw3U0/Tm6LljHls0R87nK3XRvgni0pV3UVgWM=": {
            "valueMac": {
              "type": "Buffer",
              "data": "JS8DxBmS9Al92kxQ8qmoxQc9ZD6xhO6qsjdFBX/cnL0="
            }
          },
          "M5R8ZIcgt5a+0IOIc4OKBnwMdd6gALNdTQndk8M3cyk=": {
            "valueMac": {
              "type": "Buffer",
              "data": "sVco3+HuXB4hIQGLDlazLgdXqwkUWjyCxOCqdTcFMO8="
            }
          },
          "PSC86Bht7iF+l2VyL9jCdWjw4NhSGI3NApEU5S66Qqo=": {
            "valueMac": {
              "type": "Buffer",
              "data": "RpgwV9dB+hpWAqPS48f5HPfdzgOY+OK1ESycxcfbpJQ="
            }
          },
          "AI6sHXLzUyV/z4yTxUpYF8ZngkL6+DfpLrmApSTmU7Y=": {
            "valueMac": {
              "type": "Buffer",
              "data": "A6Jw8POUHBrnFhxtaLc2Q+dPUUI1+pQn34qCNfRL+/M="
            }
          },
          "+0oPkyYuk5OwQxeyrIvnrrzXr+M6U66D71aWKUbZqXY=": {
            "valueMac": {
              "type": "Buffer",
              "data": "rrvSrsco++4c3pq8Kekh3psf88z8sxBwaHdtIxcVYEs="
            }
          }
        }
      },
      "regular_high": {
        "version": 4,
        "hash": {
          "type": "Buffer",
          "data": "djGPr1le/n8AWKtXD9L3QYJ+e8boWOSTiAIa+ZVA1dqnJM0aFO64+bqVDCtXe50l4IozwutyJd+KHJeR3ljHE5JqLilEjW3CzwPZVAxz9hOxpdj84Vxe2bQIkfg1I4kYGvv6No4Jha1oYP/uhi6S2PJOqRdR1sthIlWZxglgku0="
        },
        "indexValueMap": {
          "YEQ37i5lbvf+Hl7s7yzBhhEYp6m1UMqR/2AquQE12Uk=": {
            "valueMac": {
              "type": "Buffer",
              "data": "dda35ESiyNsypa74f2PtSu2FwE6VsROjxE4PqwB6T3s="
            }
          },
          "TiI2DICzpRiA4lYGeWno8stXin5rnYZAFBA0515lR+0=": {
            "valueMac": {
              "type": "Buffer",
              "data": "CEbyLfumg5viPlW33h4LMWGbZiGr1xtrCA2nN9UKmAY="
            }
          },
          "0MfwmW/A27zardqyLXchBX+1euIwJwaKK41ZSMreADQ=": {
            "valueMac": {
              "type": "Buffer",
              "data": "LQ+im+r9DuVKzswuif/tzVJS6Pyxm2c1tlSti1yM4Xs="
            }
          },
          "8hIiAjhu5cSbR185FzLgYf0hKcmTKfnqus+HvP5il9U=": {
            "valueMac": {
              "type": "Buffer",
              "data": "STatcsFB86dwvfCSdmi5MuJU/24ZMg9dMxrcS3ckVOk="
            }
          }
        }
      },
      "regular_low": {
        "version": 4,
        "hash": {
          "type": "Buffer",
          "data": "3e/L2RlOmLtgqOdOhlfoPIGuknnHBTjZi2Q0uVQJ3kOyYWd7QJ+MQ3GRt0u6u8zl4ZFeXS3z8/jT6IfMhWHKsWg41x8zhVIrW7wBT6Fn9dpxp+hK6tzsmvUOGhavy+3c4JgnoDH9U6UGUOPfkVsnC30Z47iryGoGluGy/MODOf4="
        },
        "indexValueMap": {
          "D7DnM2wWDtei7W+HKe2+ZNwzddCgg5k5kn22bT2Ltbw=": {
            "valueMac": {
              "type": "Buffer",
              "data": "XeTc1ot5m1uOegcxwaAEw1wfSuc9x+rsfInISFixTuM="
            }
          },
          "DbJgFGerKDp8Y3RF86Btc6Zfcfs1zkaVnyCIa7hCs6E=": {
            "valueMac": {
              "type": "Buffer",
              "data": "IC+/4Y+QbR+rEjkinDHRXFav0oTc6hc1wXQnL60+5gg="
            }
          },
          "rxb8R3nzt0qb6OhIWFZRMs9KAFaa1QbGybz0yNjq8iw=": {
            "valueMac": {
              "type": "Buffer",
              "data": "H9+ki28z/CUCX6dsFYMcWvB2xYsTXqPYhKiqWy20T5c="
            }
          },
          "iTRqQNRCvvrHJtHPzrG96Sh11aCBGOM7IdIvL36FwgI=": {
            "valueMac": {
              "type": "Buffer",
              "data": "x7DCc29FTZn+/+Fi9V86gv3GBp5JUiobWlBW+pd1Vf0="
            }
          }
        }
      }
    }
  }
}